tsimcne-0.4.24.dist-info/METADATA
tsimcne-0.4.24.dist-info/WHEEL
tsimcne-0.4.24.dist-info/entry_points.txt
tsimcne/__init__.py
tsimcne/ffcv_augmentation.py
tsimcne/imagedistortions.py
tsimcne/losses/infonce.py
tsimcne/lrschedule.py
tsimcne/models/mutate_model.py
tsimcne/models/simclr_like.py
tsimcne/tsimcne.py
tsimcne-0.4.24.dist-info/RECORD
