Metadata-Version: 2.1
Name: tsimcne
Version: 0.4.24
Summary: Visualization tool for unsupervised image visualization (ICLR 2023)
Author-Email: =?utf-8?q?Jan_Niklas_B=C3=B6hm?= <jan-niklas.boehm@uni-tuebingen.de>
License: EUPL
Project-URL: homepage, https://github.com/berenslab/t-simcne
Project-URL: documentation, https://t-simcne.readthedocs.io/en/latest
Requires-Python: >=3.10
Requires-Dist: torch>=2.4
Requires-Dist: torchvision~=0.19
Requires-Dist: lightning>=2.4
Requires-Dist: numpy>=1.24.0
Requires-Dist: scipy>=1.0.0
Requires-Dist: scikit-learn>=1.0.0
Requires-Dist: pillow
Provides-Extra: annoy
Requires-Dist: annoy>=1.17.2; extra == "annoy"
